.gitlab-ci.yml
.travis.yml
CHANGES.rst
CONTRIBUTORS.rst
DEVELOP.rst
LICENSE.GPL
LICENSE.rst
MANIFEST.in
README.rst
requirements.txt
setup.cfg
setup.py
docs/index.rst
src/redturtle/__init__.py
src/redturtle.drawio.egg-info/PKG-INFO
src/redturtle.drawio.egg-info/SOURCES.txt
src/redturtle.drawio.egg-info/dependency_links.txt
src/redturtle.drawio.egg-info/entry_points.txt
src/redturtle.drawio.egg-info/namespace_packages.txt
src/redturtle.drawio.egg-info/not-zip-safe
src/redturtle.drawio.egg-info/requires.txt
src/redturtle.drawio.egg-info/top_level.txt
src/redturtle/drawio/__init__.py
src/redturtle/drawio/configure.zcml
src/redturtle/drawio/interfaces.py
src/redturtle/drawio/permissions.zcml
src/redturtle/drawio/setuphandlers.py
src/redturtle/drawio/testing.py
src/redturtle/drawio/upgrades.py
src/redturtle/drawio/upgrades.zcml
src/redturtle/drawio/browser/__init__.py
src/redturtle/drawio/browser/configure.zcml
src/redturtle/drawio/browser/view.py
src/redturtle/drawio/browser/static/.gitkeep
src/redturtle/drawio/browser/templates/view.pt
src/redturtle/drawio/content/__init__.py
src/redturtle/drawio/content/drawio_item.py
src/redturtle/drawio/content/drawio_item.xml
src/redturtle/drawio/locales/redturtle.drawio.pot
src/redturtle/drawio/locales/update.sh
src/redturtle/drawio/locales/it/LC_MESSAGES/redturtle.drawio.mo
src/redturtle/drawio/locales/it/LC_MESSAGES/redturtle.drawio.po
src/redturtle/drawio/profiles/default/browserlayer.xml
src/redturtle/drawio/profiles/default/metadata.xml
src/redturtle/drawio/profiles/default/registry.xml
src/redturtle/drawio/profiles/default/rolemap.xml
src/redturtle/drawio/profiles/default/types.xml
src/redturtle/drawio/profiles/default/types/DrawioItem.xml
src/redturtle/drawio/profiles/uninstall/browserlayer.xml
src/redturtle/drawio/tests/__init__.py
src/redturtle/drawio/tests/test_ct_drawio_item.py
src/redturtle/drawio/tests/test_invariant.py
src/redturtle/drawio/tests/test_robot.py
src/redturtle/drawio/tests/test_setup.py
src/redturtle/drawio/tests/robot/test_ct_drawio_item.robot
src/redturtle/drawio/tests/robot/test_example.robot